{
  "autopublicacoes": [
    {
      "codigo": "7188112",
      "titulo": "33/2025",
      "data": "2025-05-04 18:50:15",
      "cod_registro_info_sfinge": null,
      "municipio": "Siderópolis",
      "entidade": "Prefeitura Municipal de Siderópolis",
      "categoria": "Outras publicações",
      "link": "https://www.diariomunicipal.sc.gov.br/?q=id:7188112",
      "texto": "<html xmlns=\"http://www.w3.org/1999/xhtml\">\n\n    <head>\n\n        <meta name=\"cp:revision\" content=\"3\"/>\n\n        <meta name=\"extended-properties:AppVersion\" content=\"16.0000\"/>\n\n        <meta name=\"meta:paragraph-count\" content=\"1\"/>\n\n        <meta name=\"meta:word-count\" content=\"141\"/>\n\n        <meta name=\"extended-properties:Application\" content=\"Microsoft Office Word\"/>\n\n        <meta name=\"meta:last-author\" content=\"Miguel Comin\"/>\n\n        <meta name=\"dc:creator\" content=\"PREFEITURA\"/>\n\n        <meta name=\"extended-properties:Company\" content=\"\"/>\n\n        <meta name=\"xmpTPg:NPages\" content=\"1\"/>\n\n        <meta name=\"dcterms:created\" content=\"2025-05-04T21:44:00Z\"/>\n\n        <meta name=\"meta:line-count\" content=\"6\"/>\n\n        <meta name=\"dcterms:modified\" content=\"2025-05-04T21:49:00Z\"/>\n\n        <meta name=\"meta:character-count\" content=\"764\"/>\n\n        <meta name=\"extended-properties:Template\" content=\"Normal\"/>\n\n        <meta name=\"meta:character-count-with-spaces\" content=\"904\"/>\n\n        <meta name=\"X-TIKA:Parsed-By\" content=\"org.apache.tika.parser.CompositeParser\"/>\n\n        <meta name=\"X-TIKA:Parsed-By\" content=\"org.apache.tika.parser.DefaultParser\"/>\n\n        <meta name=\"X-TIKA:Parsed-By\" content=\"org.apache.tika.parser.microsoft.ooxml.OOXMLParser\"/>\n\n        <meta name=\"extended-properties:DocSecurityString\" content=\"None\"/>\n\n        <meta name=\"extended-properties:TotalTime\" content=\"5\"/>\n\n        <meta name=\"Content-Length\" content=\"13132\"/>\n\n        <meta name=\"meta:page-count\" content=\"1\"/>\n\n        <meta name=\"Content-Type\" content=\"application/vnd.openxmlformats-officedocument.wordprocessingml.document\"/>\n\n        <meta name=\"dc:publisher\" content=\"\"/>\n\n        <title>&#0;</title>\n\n    </head>\n\n    <body>\n        <p>\n            <b>MUNIC&Iacute;PIO DE SIDER&Oacute;POLIS</b>\n        </p>\n\n        <p>\n            <b>PROCESSO DE LICITA&Ccedil;&Atilde;O PMS 33/2025</b>\n        </p>\n\n        <p>\n            <b>EDITAL DE PREG&Atilde;O ELETR&Ocirc;NICO PMS N&ordm; 16/2025</b>\n        </p>\n\n        <p>\n            <b>AVISO DE ALTERA&Ccedil;&Atilde;O DE DATA DO CERTAME</b>\n        </p>\n\n        <p/>\n\n        <p>O Munic&iacute;pio de Sider&oacute;polis torna p&uacute;blico que a data da sess&atilde;o p&uacute;blica do Preg&atilde;o Eletr&ocirc;nico PMS n&ordm; 16/2025, referente ao Processo de Licita&ccedil;&atilde;o PMS 33/2025, cujo objeto &eacute; o Registro de Pre&ccedil;os para fornecimento parcelado de materiais de limpeza, copa e cozinha e outros materiais de consumo, conforme as necessidades das Secretarias requisitantes, foi alterada de 06/05/2025 para \n            <b>08/05/2025 &agrave;s 09h00 min</b>. A sess&atilde;o p&uacute;blica ser&aacute; realizada exclusivamente pela plataforma www.bnc.org.br. O edital na &iacute;ntegra e demais disposi&ccedil;&otilde;es permanecem dispon&iacute;veis no site www.sideropolis.sc.gov.br e na referida plataforma. Informa&ccedil;&otilde;es adicionais podem ser obtidas pelo e-mail licitacao@sideropolis.sc.gov.br ou pelo telefone (48) 3435-8900.\n        </p>\n\n        <p>Sider&oacute;polis, 05 de maio de 2025</p>\n\n        <p/>\n\n        <p/>\n\n        <p/>\n\n        <p/>\n\n        <p/>\n\n        <p/>\n\n        <p/>\n\n        <p/>\n\n        <p/>\n\n    </body>\n</html>\n",
      "url": "https://www.diariomunicipal.sc.gov.br/arquivosbd/atos/2025/05/1746395384_33_2025_aviso_alterao_extrato.pdf"
    },
    {
      "codigo": "7188113",
      "titulo": "34/2025",
      "data": "2025-05-04 18:50:19",
      "cod_registro_info_sfinge": null,
      "municipio": "Siderópolis",
      "entidade": "Prefeitura Municipal de Siderópolis",
      "categoria": "Outras publicações",
      "link": "https://www.diariomunicipal.sc.gov.br/?q=id:7188113",
      "texto": "<html xmlns=\"http://www.w3.org/1999/xhtml\">\n\n    <head>\n\n        <meta name=\"cp:revision\" content=\"1\"/>\n\n        <meta name=\"extended-properties:AppVersion\" content=\"16.0000\"/>\n\n        <meta name=\"meta:paragraph-count\" content=\"2\"/>\n\n        <meta name=\"meta:word-count\" content=\"158\"/>\n\n        <meta name=\"extended-properties:Application\" content=\"Microsoft Office Word\"/>\n\n        <meta name=\"meta:last-author\" content=\"Miguel Comin\"/>\n\n        <meta name=\"dc:creator\" content=\"Miguel Comin\"/>\n\n        <meta name=\"extended-properties:Company\" content=\"\"/>\n\n        <meta name=\"xmpTPg:NPages\" content=\"1\"/>\n\n        <meta name=\"dcterms:created\" content=\"2025-05-04T21:47:00Z\"/>\n\n        <meta name=\"meta:line-count\" content=\"7\"/>\n\n        <meta name=\"dcterms:modified\" content=\"2025-05-04T21:48:00Z\"/>\n\n        <meta name=\"meta:character-count\" content=\"856\"/>\n\n        <meta name=\"extended-properties:Template\" content=\"Normal\"/>\n\n        <meta name=\"meta:character-count-with-spaces\" content=\"1012\"/>\n\n        <meta name=\"X-TIKA:Parsed-By\" content=\"org.apache.tika.parser.CompositeParser\"/>\n\n        <meta name=\"X-TIKA:Parsed-By\" content=\"org.apache.tika.parser.DefaultParser\"/>\n\n        <meta name=\"X-TIKA:Parsed-By\" content=\"org.apache.tika.parser.microsoft.ooxml.OOXMLParser\"/>\n\n        <meta name=\"extended-properties:DocSecurityString\" content=\"None\"/>\n\n        <meta name=\"extended-properties:TotalTime\" content=\"1\"/>\n\n        <meta name=\"Content-Length\" content=\"14574\"/>\n\n        <meta name=\"meta:page-count\" content=\"1\"/>\n\n        <meta name=\"Content-Type\" content=\"application/vnd.openxmlformats-officedocument.wordprocessingml.document\"/>\n\n        <meta name=\"dc:publisher\" content=\"\"/>\n\n        <title>&#0;</title>\n\n    </head>\n\n    <body>\n        <p>\n            <b>MUNIC&Iacute;PIO DE SIDER&Oacute;POLIS</b>\n        </p>\n\n        <p>\n            <b>PROCESSO DE LICITA&Ccedil;&Atilde;O PMS 34/2025</b>\n        </p>\n\n        <p>\n            <b>EDITAL DE PREG&Atilde;O ELETR&Ocirc;NICO PMS N&ordm; 17/2025</b>\n        </p>\n\n        <p>\n            <b>AVISO DE ALTERA&Ccedil;&Atilde;O DE DATA DO CERTAME</b>\n        </p>\n\n        <p/>\n\n        <p>O Munic&iacute;pio de Sider&oacute;polis torna p&uacute;blico que a data da sess&atilde;o p&uacute;blica do Preg&atilde;o Eletr&ocirc;nico PMS n&ordm; 17/2025, referente ao Processo de Licita&ccedil;&atilde;o PMS 34/2025, cujo objeto &eacute; o Registro de Pre&ccedil;os para contrata&ccedil;&atilde;o de servi&ccedil;os de manuten&ccedil;&atilde;o, conserva&ccedil;&atilde;o e implanta&ccedil;&atilde;o de sinaliza&ccedil;&atilde;o horizontal, vertical e de dispositivos de seguran&ccedil;a nas vias do munic&iacute;pio de Sider&oacute;polis, com fornecimento de materiais, conforme quantidades e exig&ecirc;ncias estabelecidas no edital, foi alterada de 06/05/2025 para \n            <b>09/05/2025 &agrave;s 13h30 min</b>. A sess&atilde;o p&uacute;blica ser&aacute; realizada exclusivamente pela plataforma www.bnc.org.br. O edital na &iacute;ntegra e demais disposi&ccedil;&otilde;es permanecem dispon&iacute;veis no site www.sideropolis.sc.gov.br e na referida plataforma. Informa&ccedil;&otilde;es adicionais podem ser obtidas pelo e-mail licitacao@sideropolis.sc.gov.br ou pelo telefone (48) 3435-8900.\n        </p>\n\n        <p>Sider&oacute;polis, 05 de maio de 2025</p>\n\n        <p/>\n\n        <p/>\n\n        <p/>\n\n        <p/>\n\n        <p/>\n\n        <p/>\n\n        <p/>\n\n        <p/>\n\n    </body>\n</html>\n",
      "url": "https://www.diariomunicipal.sc.gov.br/arquivosbd/atos/2025/05/1746395408_34_2025_aviso_alterao_extrato.pdf"
    }
  ]
}